pubsub/__init__.py
pubsub/publisher.py
pubsub/subscriber.py
pubsub_yarmenti-0.2.2.dist-info/LICENSE
pubsub_yarmenti-0.2.2.dist-info/METADATA
pubsub_yarmenti-0.2.2.dist-info/WHEEL
pubsub_yarmenti-0.2.2.dist-info/top_level.txt
pubsub_yarmenti-0.2.2.dist-info/RECORD
